businessdate/__init__.py
businessdate/basedate.py
businessdate/businessdate.py
businessdate/businessholidays.py
businessdate/businessperiod.py
businessdate/businessrange.py
businessdate/businessschedule.py
businessdate/conventions.py
businessdate/daycount.py
businessdate/ymd.py
businessdate-0.5.dist-info/LICENSE
businessdate-0.5.dist-info/METADATA
businessdate-0.5.dist-info/WHEEL
businessdate-0.5.dist-info/top_level.txt
businessdate-0.5.dist-info/RECORD
